scorner/__init__.py
scorner/demo.py
scorner/scorner.py
scorner-0.2.0.dist-info/licenses/LICENSE
scorner_scurran/__init__.py
scorner_scurran/demo.py
scorner_scurran/scorner.py
scorner-0.2.0.dist-info/METADATA
scorner-0.2.0.dist-info/WHEEL
scorner-0.2.0.dist-info/top_level.txt
scorner-0.2.0.dist-info/RECORD
