Metadata-Version: 2.4
Name: scorner
Version: 0.2.0
Summary: Produces a similar plot to  corner.py, but uses seaborn to produce a more adjustable, 'publication ready' plot
Author-email: Stephen Curran <scurran.astro@gmail.com>
Project-URL: Homepage, https://github.com/steviecurran/scorner
Classifier: Programming Language :: Python :: 3
Classifier: Operating System :: OS Independent
Requires-Python: >=3.9
License-File: LICENSE
Dynamic: license-file
